{"commits":[{"author":"Matthew Barr","date":"2013-08-20T23:58:51-04:00","commit":"eea6a16ff1383c4b0e04e26f508f89db37dfeee1","summary":"updated description &amp; contact info for the bundle."},{"author":"Michael Sheets","date":"2013-08-11T19:06:41-05:00","commit":"a0242931662f7807d0d4ac3528a8450a27348317","summary":"Update README"},{"body":"This is to prevent doing something the user does not expect after simply installing a bundle. Leaving the command but having it disabled allows the user to simply check a box should they want this feature.","author":"Michael Sheets","date":"2013-08-11T18:57:20-05:00","commit":"107ecd2ef1a4bd9a701148ffbd1f91e13ade232b","summary":"Disable Validate on Save command by default"},{"author":"Michael Sheets","date":"2013-08-11T18:38:25-05:00","commit":"fdbb3d4b09b80c0ca496196b219a27ea2b2533b4","summary":"Implement requiredCommands"},{"body":"As this is run via a callback now it no longer needs to be a menu item.","author":"Michael Sheets","date":"2013-08-11T17:14:43-05:00","commit":"2e8f8310b308523cac50a1bcf1d301f824d23336","summary":"Remove Validate On Save from menu"},{"author":"Michael Sheets","date":"2013-08-10T19:30:56-05:00","commit":"b6ee40fdaa524b21f872dde4e8a3c0fb43beebc5","summary":"Use semanticClass callback to run after save"},{"author":"Michael Sheets","date":"2013-08-11T18:52:50-05:00","commit":"cf8b8df92402c630d2cf8e30c9c5567ab60bd37f","summary":"Return true at end of command to prevent error"},{"author":"Michael Sheets","date":"2013-08-10T19:06:58-05:00","commit":"6707acdc812c99e57492c61acb62870d78e8d199","summary":"Add scope to whitespace prefixing a line comment"},{"author":"Michael Sheets","date":"2013-08-11T18:48:34-05:00","commit":"14a27bfca71569f8540967c2cda523ac787cba04","summary":"Quote filepaths to allow for spaces in filenames"},{"author":"Michael Sheets","date":"2013-08-11T15:51:46-05:00","commit":"76bc7b66e011ff4331dc0b70564b27f0d262f8f2","summary":"Limit string escapes to valid sequences"},{"body":"This will be converted upon insertion into the current tab style/size.","author":"Michael Sheets","date":"2013-08-10T18:57:35-05:00","commit":"5bd0fa4650850aa46d6ae5eb7803a70c4d93cb33","summary":"Use literal tab character in snippets"},{"author":"Michael Sheets","date":"2013-08-10T18:56:40-05:00","commit":"bcdadcc46ebde8cd5c94a4af76a4e9d16ecff527","summary":"Re-organize menu layout"},{"body":"This is likely not inclusive, I wasn't able to find a spec for the allowed characters.","author":"Michael Sheets","date":"2013-08-10T17:56:43-05:00","commit":"c4612086efb7136d850d6c5ecd1a3fc812fd9f15","summary":"Allow / and . inside strings when indenting"},{"author":"Michael Sheets","date":"2013-08-10T17:52:10-05:00","commit":"b9f9828f46645c502e1e042a212e3d096a8dea3d","summary":"Do not scope surrounding whitespace as a constant"},{"author":"Michael Sheets","date":"2013-08-10T17:51:01-05:00","commit":"feb2b3f2d581d3efd9b739ee61be2dea2214d7a7","summary":"Add and extend several punctuation scopes"},{"body":"Let's get rid of it. We might revisit this if we want to be able to align\nparameters of functions when split over several lines (which is quite\nunfrequent in Puppet manifests).\n\nSigned-off-by: brice &lt;brice@daysofwonder.com>","author":"brice","date":"2013-06-15T15:47:37+02:00","commit":"24e8776a668f759cecf01711a91f954ad950ee7f","summary":"Fix #3 - indentNextLinePattern is unused"},{"body":"Fixes #1","author":"Matthew Barr","date":"2013-06-14T10:37:26-04:00","commit":"848159374d62e54ed52909e9bbd23e374d40df71","summary":"Added source.puppet to scope for a few snippets"},{"body":"Fixes issue #2","author":"Matthew Barr","date":"2013-06-14T10:00:46-04:00","commit":"9a49b04e3dc819017dd66ef4e5bbee60ed17e481","summary":"Added $0 to be the same as the other snippets."},{"body":"This commit moved everything in the root directory of the repo, but\nthe previous commit was merged as it was in the previous location...\n\nSigned-off-by: brice &lt;brice@daysofwonder.com>","author":"brice","date":"2013-06-05T20:21:43+02:00","commit":"343faa7e8e3a952f26d455b330c3203e6e9e1d1b","summary":"Update Indentation Preferences location since dbdbd0"},{"author":"Brice Figureau","date":"2012-07-13T10:35:26+02:00","commit":"8c7f5c01ab44346f93b325e8d94984458b56151c","summary":"Add some indentation preferences for Puppet"},{"author":"Brice Figureau","date":"2012-07-13T10:34:57+02:00","commit":"c02300d0ae90fef63e18fcf1a1945c8a234d2813","summary":"Changed snippets so that it's easier to add parameters"},{"author":"Brice Figureau","date":"2012-07-13T10:34:20+02:00","commit":"a9bdd4157b91d9c1d5609f76aa0dccf7baccce6c","summary":"Added a bunch of completion"},{"author":"Matthew Barr","date":"2013-06-04T21:42:44-04:00","commit":"36d0535b59fa04eadf76224ecdf69d70ddd4cd2f","summary":"Switch the puppet parser to use html vs no color"},{"author":"Matthew Barr","date":"2013-06-04T21:24:33-04:00","commit":"276b8489c277561136378ba8163102cc780efefc","summary":"updated Readme to make things more readable &amp; useful"},{"author":"Matthew Barr","date":"2013-06-04T21:10:01-04:00","commit":"0e090f0ddead8965c20109679430f1ffa0813ccd","summary":"removed unnecessary README.md"},{"author":"Maximilian Gaß","date":"2013-05-06T10:58:45+02:00","commit":"64c227813d15f68ff0ccdc22134094b418fe8e9f","summary":"add node snippets"},{"author":"Matthew Barr","date":"2013-06-04T09:20:56-04:00","commit":"0ba0ce32bc2c182da9cae7f0b0ee312f544ec4b8","summary":"Updated spelling on README"},{"author":"Matthew Barr","date":"2013-03-11T15:40:18-04:00","commit":"9205739b7720baf6c1f566d3b3b93de0c561305d","summary":"change package to be a single quote"},{"author":"Matthew Barr","date":"2012-11-02T00:59:30-04:00","commit":"77248adc3404c3878e73dac92c8171abc85f2fcb","summary":"updated file  expansion"},{"author":"Markus Strauss","date":"2012-10-03T21:37:40-04:00","commit":"cafd981b80a398ab56f31ebbba0a2f3d693f4c5a","summary":"converted README to markdown"},{"author":"Markus Strauss","date":"2012-10-03T21:31:50-04:00","commit":"a138a81e9a1a0f10ff73abb7373cb22259a41b0c","summary":"update README for TextMate 2"},{"author":"Silvano Buback","date":"2012-06-29T16:42:32-03:00","commit":"20117e728ea4c5f83c58c9d8734daec711159613","summary":"better readme"},{"author":"Silvano Buback","date":"2012-06-29T16:40:02-03:00","commit":"62be72ab2a184b09762b76421158b79e17acfb62","summary":"better readme"},{"author":"Silvano Buback","date":"2012-06-29T16:24:33-03:00","commit":"98b68f5da9ec8b560e05179ed5d6bb6df3bebc56","summary":"correções finais"},{"author":"Silvano Buback","date":"2012-06-29T16:21:00-03:00","commit":"2322f4f1c71638749d70b7dcf8645bc1c8fad873","summary":"customização final do relatório"},{"author":"Silvano Buback","date":"2012-06-29T16:02:16-03:00","commit":"2fc190c3cb5b430df5b9f039744ffb6925377b4d","summary":"correção no report mode"},{"author":"Silvano Buback","date":"2012-06-29T15:58:37-03:00","commit":"aed6a0296705e0cad2cf720a494ba4e0cc77ddf6","summary":"correção do info.plist"},{"author":"Silvano Buback","date":"2012-06-29T15:47:49-03:00","commit":"18f778e92b920f5a26421a917309da8bc559e939","summary":"report mode corrigido"},{"author":"Silvano Buback","date":"2012-06-29T15:19:18-03:00","commit":"7ffebe3f5425e8d016e2f12fd3cace9d37b9f13c","summary":"versoes preliminares"},{"author":"Silvano Buback","date":"2012-06-29T15:06:49-03:00","commit":"5359efda1d64b6b923a4d39b6445436f3830b4bc","summary":"Adicionado suporte ao validate on save e relatorio de erros do projeto inteiro"}],"name":"Puppet","web":"https://github.com/puppet-textmate-bundle/puppet-textmate-bundle/commit/"}